EroManga2Epub-0.3.dist-info/METADATA
EroManga2Epub-0.3.dist-info/RECORD
EroManga2Epub-0.3.dist-info/WHEEL
EroManga2Epub-0.3.dist-info/entry_points.txt
EroManga2Epub-0.3.dist-info/top_level.txt
eroepub/__init__.py
eroepub/main.py
eroepub/utils.py
eroepub/epub_generator/__init__.py
eroepub/epub_generator/epub_builder.py
eroepub/epub_generator/file_templates.py
eroepub/epub_generator/images_processor.py
eroepub/epub_generator/manifest_generator.py
eroepub/epub_generator/xhtml_generator.py
