Metadata-Version: 2.1
Name: EroManga2Epub
Version: 0.3
Summary: Transform EroManga from dir to epub.
Home-page: UNKNOWN
Author: Pandaria
Author-email: pandaria98f@gmail.com
License: UNKNOWN
Platform: UNKNOWN
Requires-Dist: Pillow
